fiddlecube.py
fiddlecube-0.1.9.dist-info/METADATA
fiddlecube-0.1.9.dist-info/WHEEL
fiddlecube-0.1.9.dist-info/RECORD
