Metadata-Version: 2.1
Name: fiddlecube
Version: 0.1.9
Summary: Generate ideal question-answer dataset for testing your LLM.
Author: Kaushik Srinivasan
Author-email: kaushik@fiddlecube.ai
Requires-Python: >=3.9,<3.13
Classifier: Programming Language :: Python :: 3
Classifier: Programming Language :: Python :: 3.9
Classifier: Programming Language :: Python :: 3.10
Classifier: Programming Language :: Python :: 3.11
Requires-Dist: requests (>=2.32.3,<3.0.0)
